{
  "ticker": "AFG",
  "name": "AF GRUPPEN",
  "dividends": [
    {
      "date": "2016-05-13",
      "amount": 5.0
    },
    {
      "date": "2016-11-16",
      "amount": 3.0
    },
    {
      "date": "2017-05-15",
      "amount": 3.75
    },
    {
      "date": "2017-11-13",
      "amount": 3.5
    },
    {
      "date": "2018-05-11",
      "amount": 5.0
    },
    {
      "date": "2018-11-12",
      "amount": 3.5
    },
    {
      "date": "2019-05-16",
      "amount": 5.0
    },
    {
      "date": "2019-12-12",
      "amount": 7.0
    },
    {
      "date": "2020-05-18",
      "amount": 6.0
    },
    {
      "date": "2020-11-16",
      "amount": 3.5
    },
    {
      "date": "2021-05-12",
      "amount": 6.5
    },
    {
      "date": "2021-11-15",
      "amount": 4.0
    },
    {
      "date": "2022-05-16",
      "amount": 6.5
    },
    {
      "date": "2022-11-15",
      "amount": 4.0
    },
    {
      "date": "2023-05-15",
      "amount": 6.5
    },
    {
      "date": "2024-05-16",
      "amount": 3.5
    },
    {
      "date": "2025-05-16",
      "amount": 5.0
    },
    {
      "date": "2025-11-18",
      "amount": 4.0
    }
  ],
  "last_updated": "2026-05-04"
}