{
  "ticker": "BONHR",
  "name": "BONHEUR",
  "dividends": [
    {
      "date": "2016-05-27",
      "amount": 2.0
    },
    {
      "date": "2017-05-26",
      "amount": 2.0
    },
    {
      "date": "2018-05-31",
      "amount": 2.0
    },
    {
      "date": "2019-05-29",
      "amount": 4.0
    },
    {
      "date": "2020-05-28",
      "amount": 4.3
    },
    {
      "date": "2021-05-28",
      "amount": 4.0
    },
    {
      "date": "2022-05-27",
      "amount": 4.3
    },
    {
      "date": "2023-05-26",
      "amount": 5.0
    },
    {
      "date": "2024-05-24",
      "amount": 6.0
    },
    {
      "date": "2025-05-23",
      "amount": 6.75
    }
  ],
  "last_updated": "2026-05-04",
  "year_end_prices": {
    "2016": 59.7851,
    "2017": 76.2268,
    "2018": 80.9162,
    "2019": 176.2294,
    "2020": 218.6518,
    "2021": 326.6215,
    "2022": 267.1411,
    "2023": 229.3504,
    "2024": 253.6594,
    "2025": 251.5,
    "2026": 268.5
  }
}