{
  "ticker": "HSPG",
  "name": "H\u00d8LAND OG SETSKOG",
  "dividends": [
    {
      "date": "2017-02-28",
      "amount": 5.0
    },
    {
      "date": "2018-02-28",
      "amount": 5.0
    },
    {
      "date": "2019-02-28",
      "amount": 7.5
    },
    {
      "date": "2020-02-28",
      "amount": 8.0
    },
    {
      "date": "2022-03-11",
      "amount": 7.0
    },
    {
      "date": "2023-03-10",
      "amount": 7.0
    },
    {
      "date": "2024-03-15",
      "amount": 7.0
    },
    {
      "date": "2025-03-20",
      "amount": 9.0
    },
    {
      "date": "2026-03-20",
      "amount": 5.0
    }
  ],
  "last_updated": "2026-05-11",
  "year_end_prices": {
    "2016": 62.5539,
    "2017": 66.8874,
    "2018": 64.0348,
    "2019": 86.5126,
    "2020": 99.5133,
    "2021": 113.6175,
    "2022": 130.214,
    "2023": 111.7875,
    "2024": 132.2102,
    "2025": 147.7344,
    "2026": 161.0
  }
}