{
  "ticker": "MELG",
  "name": "MELHUS SPAREBANK",
  "last_updated": "2026-05-06",
  "valuation": {
    "market_cap": 532175424.0,
    "enterprise_value": 2585949184.0,
    "trailing_pe": 13.22314,
    "forward_pe": 13.684961,
    "peg_ratio": null,
    "price_to_sales": 1.582447,
    "price_to_book": 0.334603,
    "ev_to_revenue": 7.689,
    "ev_to_ebitda": null
  },
  "per_share": {
    "current_price": 192.0,
    "eps_trailing": 14.52,
    "eps_forward": 14.03,
    "book_value": 573.814,
    "revenue_per_share": 121.135,
    "currency": "NOK"
  },
  "profitability": {
    "profit_margin": 0.41672,
    "operating_margin": 0.50131,
    "gross_margin": 0.0,
    "ebitda_margin": 0.0,
    "roe": 0.08582,
    "roa": 0.01211
  },
  "income": {
    "total_revenue": 336299008.0,
    "revenue_growth": -0.036,
    "gross_profits": 336299008.0,
    "ebitda": null,
    "net_income": 40269000.0,
    "earnings_growth": -0.219
  },
  "balance_sheet": {
    "total_cash": 478993984.0,
    "cash_per_share": 172.534,
    "total_debt": 2531908096.0,
    "debt_to_equity": null,
    "current_ratio": null,
    "quick_ratio": null
  },
  "trading": {
    "beta": 0.186,
    "week52_high": 206.0,
    "week52_low": 167.0,
    "avg50d": 193.4544,
    "avg200d": 184.9925,
    "avg_volume": 805.0,
    "avg_volume_10d": 466.0,
    "shares_outstanding": 2771746.0,
    "float_shares": 2775809.0,
    "insider_ownership": 0.42674,
    "institutional_ownership": 0.08697,
    "short_ratio": null
  },
  "_pe_label": "13.22x"
}